common_py_config/__init__.py
common_py_config/configs/mypy.ini
common_py_config/configs/noxfile.py
common_py_config/configs/ruff.toml
common_py_config/pytest_common_plugin.py
common_py_config-0.1.2.dist-info/METADATA
common_py_config-0.1.2.dist-info/WHEEL
common_py_config-0.1.2.dist-info/entry_points.txt
common_py_config-0.1.2.dist-info/RECORD
